.DS_Store
demo2024ceu/__init__.py
demo2024ceu/first.py
demo2024ceu-1.1.dist-info/METADATA
demo2024ceu-1.1.dist-info/WHEEL
demo2024ceu-1.1.dist-info/top_level.txt
demo2024ceu-1.1.dist-info/RECORD
