Metadata-Version: 2.1
Name: demo2024ceu
Version: 1.1
Summary: Demo package
Home-page: https://github.com/misrori/demopackagepy
Author: Bomsk
Author-email: 
License: MIT
Platform: UNKNOWN
